movies_api/__init__.py
movies_api/admin.py
movies_api/apps.py
movies_api/forms.py
movies_api/models.py
movies_api/tests.py
movies_api/urls.py
movies_api/utils.py
movies_api/views.py
netguru_recruitment_task_adrian-1.1.dist-info/METADATA
netguru_recruitment_task_adrian-1.1.dist-info/WHEEL
netguru_recruitment_task_adrian-1.1.dist-info/top_level.txt
netguru_recruitment_task_adrian-1.1.dist-info/RECORD
