Metadata-Version: 2.1
Name: netguru-recruitment-task-adrian
Version: 1.1
Summary: My implementation of Movies REST API
Home-page: https://github.com/Qentinios/netguru_recruitment_task/commits/master
Author: Adrian Czok
Author-email: theadrianczok@gmail.com
License: MIT
Platform: UNKNOWN
